perfecto/__init__.py
perfecto/delete_older_repo_new_api.py
perfecto/perfectoactions.py
perfecto/reserve_limit.py
perfectoactions-2.0.33.dist-info/LICENSE
perfectoactions-2.0.33.dist-info/METADATA
perfectoactions-2.0.33.dist-info/WHEEL
perfectoactions-2.0.33.dist-info/entry_points.txt
perfectoactions-2.0.33.dist-info/top_level.txt
perfectoactions-2.0.33.dist-info/RECORD
