Metadata-Version: 2.1
Name: perfectoactions
Version: 2.0.33
Summary: A Perfecto device actions execution + reporter package
Home-page: https://github.com/PerfectoMobileSA/Device_actions_reporter
Author: Genesis Thomas
Author-email: gthomas@perforce.com
License: GPLv3
Keywords: Perfecto,appium,selenium,testing,api,automation
Classifier: Programming Language :: Python :: 3
Classifier: License :: OSI Approved :: GNU General Public License v3 (GPLv3)
Classifier: Operating System :: OS Independent
License-File: LICENSE
Requires-Dist: DateTimeRange
Requires-Dist: typepy
Requires-Dist: requests
Requires-Dist: configparser
Requires-Dist: termcolor
Requires-Dist: pandas
Requires-Dist: matplotlib
Requires-Dist: colorama
Requires-Dist: openpyxl
Requires-Dist: xlrd
Requires-Dist: jinja2
Requires-Dist: tzlocal
Requires-Dist: ipython
Requires-Dist: xlwt
